alpiq_algo_trader/__init__.py
alpiq_algo_trader-0.0.1.dist-info/METADATA
alpiq_algo_trader-0.0.1.dist-info/WHEEL
alpiq_algo_trader-0.0.1.dist-info/RECORD
