Metadata-Version: 2.1
Name: alpiq-algo-trader
Version: 0.0.1
Summary: 
Author: lucas.jamar
Author-email: lucas.jamar@alpiq.com
Requires-Python: >=3.10,<4.0
Classifier: Programming Language :: Python :: 3
Classifier: Programming Language :: Python :: 3.10
Classifier: Programming Language :: Python :: 3.11
Classifier: Programming Language :: Python :: 3.12
